<?xml version='1.0' encoding='UTF-8' ?><rummikub-transcript>
 <setup>
  <players>
   <player id='1'>
    <name>Onbekend</name>
    <url>http://tweakers.awardspace.com/RummiDemo.php</url>
    <method>GET</method>
    <tiles>K10.G5.R11.K2.R8.G7.B11.B12.R12.G1.G11.B2.B1.R7</tiles>
   </player>
   <player id='2'>
    <name>qanar</name>
    <url>http://qanar.be/programs/rummikub.php</url>
    <method>GET</method>
    <tiles>B4.B6.B13.G3.G11.K4.R10.G2.R11.G9.B11.G5.R8.B6</tiles>
   </player>
   <player id='3'>
    <name>EdwinG</name>
    <url>http://typefreak.nl/rummikub/basic.php</url>
    <method>POST</method>
    <tiles>K6.G9.B7.G13.B8.B9.R2.B9.G7.K11.B5.K1.K7.K7</tiles>
   </player>
   <player id='4'>
    <name>GuidoH</name>
    <url>http://www.guidohendriks.nl/got/rummikub/</url>
    <method>POST</method>
    <tiles>R9.G10.K12.K1.K6.K13.G4.K11.B8.G6.B10.B3.G1.K4</tiles>
   </player>
  </players>
  <pool size='48'>G12.B10.B3.G8.R13.K2.R4.G2.B7.R3.G8.K9.K5.B4.G4.B13.K9.R9.K5.K3.R13.G13.G3.R1.G6.K3.B1.K12.R6.R3.R12.R7.R1.R5.K8.G12.K13.K8.B5.B12.G10.K10.R6.R4.B2.R5.R2.R10</pool>
 </setup>

 <turns>
  <turn no='1' player='1' rpc-delay='0.225712s'>
   <played>R11.G11.B11</played>
  <table>R11.G11.B11</table>
   <tiles value='67'>K10.G5.K2.R8.G7.B12.R12.G1.B2.B1.R7</tiles>
  </turn>
  <turn no='2' player='2' rpc-delay='0.177866s'>
   <drawn>G12</drawn>
   <pool size='47'/>
   <tiles value='115'>B4.B6.B13.G3.G11.K4.R10.G2.R11.G9.B11.G5.R8.B6.G12</tiles>
  </turn>
  <turn no='3' player='3' rpc-delay='0.0219612s'>
   <played>B7.B8.B9.K11</played>
  <table>R11.G11.B11.K11-B7.B8.B9</table>
   <tiles value='66'>K6.G9.G13.R2.B9.G7.B5.K1.K7.K7</tiles>
  </turn>
  <turn no='4' player='4' rpc-delay='0.0133587s'>
   <played>B10.K11.K12.K13</played>
  <table>R11.G11.B11.K11-B7.B8.B9.B10-K11.K12.K13</table>
   <tiles value='52'>R9.G10.K1.K6.G4.B8.G6.B3.G1.K4</tiles>
  </turn>
  <turn no='5' player='1' rpc-delay='0.447778s'>
   <played>B12.K10</played>
  <table>B7.B8.B9.B10.B11.B12-K10.K11.K12.K13-R11.G11.K11</table>
   <tiles value='45'>G5.K2.R8.G7.R12.G1.B2.B1.R7</tiles>
  </turn>
  <turn no='6' player='2' rpc-delay='0.186763s'>
   <played>B6.B11.B13</played>
  <table>B6.B7.B8.B9.B10.B11.B12.B13-K10.K11.K12.K13-R11.G11.B11.K11</table>
   <tiles value='85'>B4.G3.G11.K4.R10.G2.R11.G9.G5.R8.B6.G12</tiles>
  </turn>
  <turn no='7' player='3' rpc-delay='0.022714s'>
   <played>B5</played>
  <table>B5.B6.B7.B8.B9.B10.B11.B12.B13-K10.K11.K12.K13-R11.G11.B11.K11</table>
   <tiles value='61'>K6.G9.G13.R2.B9.G7.K1.K7.K7</tiles>
  </turn>
  <turn no='8' player='4' rpc-delay='0.0136397s'>
   <played>B8</played>
  <table>B5.B6.B7.B8-K10.K11.K12.K13-R11.G11.B11.K11-B8.B9.B10.B11.B12.B13</table>
   <tiles value='44'>R9.G10.K1.K6.G4.G6.B3.G1.K4</tiles>
  </turn>
  <turn no='9' player='1' rpc-delay='0.141316s'>
   <drawn>B10</drawn>
   <pool size='46'/>
   <tiles value='55'>G5.K2.R8.G7.R12.G1.B2.B1.R7.B10</tiles>
  </turn>
  <turn no='10' player='2' rpc-delay='0.188216s'>
   <played>B4</played>
  <table>B4.B5.B6.B7.B8-K10.K11.K12.K13-R11.G11.B11.K11-B8.B9.B10.B11.B12.B13</table>
   <tiles value='81'>G3.G11.K4.R10.G2.R11.G9.G5.R8.B6.G12</tiles>
  </turn>
  <turn no='11' player='3' rpc-delay='0.022788s'>
   <played>B9</played>
  <table>B4.B5.B6.B7.B8.B9-K10.K11.K12.K13-R11.G11.B11.K11-B8.B9.B10.B11.B12.B13</table>
   <tiles value='52'>K6.G9.G13.R2.G7.K1.K7.K7</tiles>
  </turn>
  <turn no='12' player='4' rpc-delay='0.0141785s'>
   <played>B3</played>
  <table>B3.B4.B5.B6.B7.B8.B9-K10.K11.K12.K13-R11.G11.B11.K11-B8.B9.B10.B11.B12.B13</table>
   <tiles value='41'>R9.G10.K1.K6.G4.G6.G1.K4</tiles>
  </turn>
  <turn no='13' player='1' rpc-delay='0.314077s'>
   <played>B1.B2.B10</played>
  <table>B1.B2.B3.B4.B5.B6.B7.B8.B9.B10-K10.K11.K12.K13-B8.B9.B10.B11.B12.B13-R11.G11.B11.K11</table>
   <tiles value='42'>G5.K2.R8.G7.R12.G1.R7</tiles>
  </turn>
  <turn no='14' player='2' rpc-delay='0.187335s'>
   <drawn>B3</drawn>
   <pool size='45'/>
   <tiles value='84'>G3.G11.K4.R10.G2.R11.G9.G5.R8.B6.G12.B3</tiles>
  </turn>
  <turn no='15' player='3' rpc-delay='0.0223461s'>
   <drawn>G8</drawn>
   <pool size='44'/>
   <tiles value='60'>K6.G9.G13.R2.G7.K1.K7.K7.G8</tiles>
  </turn>
  <turn no='16' player='4' rpc-delay='0.0128589s'>
   <drawn>R13</drawn>
   <pool size='43'/>
   <tiles value='54'>R9.G10.K1.K6.G4.G6.G1.K4.R13</tiles>
  </turn>
  <turn no='17' player='1' rpc-delay='0.47249s'>
   <drawn>K2</drawn>
   <pool size='42'/>
   <tiles value='44'>G5.K2.R8.G7.R12.G1.R7.K2</tiles>
  </turn>
  <turn no='18' player='2' rpc-delay='0.205059s'>
   <drawn>R4</drawn>
   <pool size='41'/>
   <tiles value='88'>G3.G11.K4.R10.G2.R11.G9.G5.R8.B6.G12.B3.R4</tiles>
  </turn>
  <turn no='19' player='3' rpc-delay='0.0227087s'>
   <played>G7.G8.G9</played>
  <table>B1.B2.B3.B4.B5.B6.B7.B8.B9.B10-K10.K11.K12.K13-B8.B9.B10.B11.B12.B13-R11.G11.B11.K11-G7.G8.G9</table>
   <tiles value='36'>K6.G13.R2.K1.K7.K7</tiles>
  </turn>
  <turn no='20' player='4' rpc-delay='0.0127168s'>
   <played>G6.G10</played>
  <table>B1.B2.B3.B4.B5.B6.B7.B8.B9.B10-K10.K11.K12.K13-B8.B9.B10.B11.B12.B13-R11.G11.B11.K11-G6.G7.G8.G9.G10</table>
   <tiles value='38'>R9.K1.K6.G4.G1.K4.R13</tiles>
  </turn>
  <turn no='21' player='1' rpc-delay='0.729352s'>
   <played>G5.G7</played>
  <table>B1.B2.B3.B4.B5.B6.B7.B8.B9.B10-K10.K11.K12.K13-B8.B9.B10.B11.B12.B13-G5.G6.G7-G7.G8.G9.G10-R11.G11.B11.K11</table>
   <tiles value='32'>K2.R8.R12.G1.R7.K2</tiles>
  </turn>
  <turn no='22' player='2' rpc-delay='0.205708s'>
   <played>G11.G12</played>
  <table>B1.B2.B3.B4.B5.B6.B7.B8.B9.B10-K10.K11.K12.K13-B8.B9.B10.B11.B12.B13-G5.G6.G7-G7.G8.G9.G10.G11.G12-R11.G11.B11.K11</table>
   <tiles value='65'>G3.K4.R10.G2.R11.G9.G5.R8.B6.B3.R4</tiles>
  </turn>
  <turn no='23' player='3' rpc-delay='0.0725978s'>
   <played>G13</played>
  <table>B1.B2.B3.B4.B5.B6.B7.B8.B9.B10-K10.K11.K12.K13-B8.B9.B10.B11.B12.B13-G5.G6.G7-G7.G8.G9.G10.G11.G12.G13-R11.G11.B11.K11</table>
   <tiles value='23'>K6.R2.K1.K7.K7</tiles>
  </turn>
  <turn no='24' player='4' rpc-delay='0.0134749s'>
   <played>G4</played>
  <table>B1.B2.B3.B4.B5.B6.B7.B8.B9.B10-K10.K11.K12.K13-B8.B9.B10.B11.B12.B13-G4.G5.G6.G7-G7.G8.G9.G10.G11.G12.G13-R11.G11.B11.K11</table>
   <tiles value='34'>R9.K1.K6.G1.K4.R13</tiles>
  </turn>
  <turn no='25' player='1' rpc-delay='0.35764s'>
   <drawn>G2</drawn>
   <pool size='40'/>
   <tiles value='34'>K2.R8.R12.G1.R7.K2.G2</tiles>
  </turn>
  <turn no='26' player='2' rpc-delay='0.188191s'>
   <played>G2.G3</played>
  <table>B1.B2.B3.B4.B5.B6.B7.B8.B9.B10-K10.K11.K12.K13-B8.B9.B10.B11.B12.B13-G2.G3.G4.G5.G6.G7-G7.G8.G9.G10.G11.G12.G13-R11.G11.B11.K11</table>
   <tiles value='60'>K4.R10.R11.G9.G5.R8.B6.B3.R4</tiles>
  </turn>
  <turn no='27' player='3' rpc-delay='0.0269793s'>
   <drawn>B7</drawn>
   <pool size='39'/>
   <tiles value='30'>K6.R2.K1.K7.K7.B7</tiles>
  </turn>
  <turn no='28' player='4' rpc-delay='0.0142137s'>
   <played>G1.K1</played>
  <table>B2.B3.B4.B5.B6.B7.B8.B9.B10-K10.K11.K12.K13-B8.B9.B10.B11.B12.B13-G2.G3.G4.G5.G6.G7-G7.G8.G9.G10.G11.G12.G13-R11.G11.B11.K11-G1.B1.K1</table>
   <tiles value='32'>R9.K6.K4.R13</tiles>
  </turn>
  <turn no='29' player='1' rpc-delay='0.071495s'>
   <played>G1</played>
  <table>B2.B3.B4.B5.B6.B7.B8.B9.B10-K10.K11.K12.K13-B8.B9.B10.B11.B12.B13-G1.G2.G3.G4.G5.G6.G7-G7.G8.G9.G10.G11.G12.G13-R11.G11.B11.K11-G1.B1.K1</table>
   <tiles value='33'>K2.R8.R12.R7.K2.G2</tiles>
  </turn>
  <turn no='30' player='2' rpc-delay='0.202081s'>
   <drawn>R3</drawn>
   <pool size='38'/>
   <tiles value='63'>K4.R10.R11.G9.G5.R8.B6.B3.R4.R3</tiles>
  </turn>
  <turn no='31' player='3' rpc-delay='0.0233126s'>
   <played>B7</played>
  <table>B2.B3.B4.B5.B6.B7-B7.B8.B9.B10-K10.K11.K12.K13-B8.B9.B10.B11.B12.B13-G1.G2.G3.G4.G5.G6.G7-G7.G8.G9.G10.G11.G12.G13-R11.G11.B11.K11-G1.B1.K1</table>
   <tiles value='23'>K6.R2.K1.K7.K7</tiles>
  </turn>
  <turn no='32' player='4' rpc-delay='0.0120036s'>
   <drawn>G8</drawn>
   <pool size='37'/>
   <tiles value='40'>R9.K6.K4.R13.G8</tiles>
  </turn>
  <turn no='33' player='1' rpc-delay='0.066805s'>
   <drawn>K9</drawn>
   <pool size='36'/>
   <tiles value='42'>K2.R8.R12.R7.K2.G2.K9</tiles>
  </turn>
  <turn no='34' player='2' rpc-delay='0.181133s'>
   <played>B6</played>
  <table>B2.B3.B4.B5.B6.B7-B6.B7.B8.B9.B10-K10.K11.K12.K13-B8.B9.B10.B11.B12.B13-G1.G2.G3.G4.G5.G6.G7-G7.G8.G9.G10.G11.G12.G13-R11.G11.B11.K11-G1.B1.K1</table>
   <tiles value='57'>K4.R10.R11.G9.G5.R8.B3.R4.R3</tiles>
  </turn>
  <turn no='35' player='3' rpc-delay='0.0225542s'>
   <drawn>K5</drawn>
   <pool size='35'/>
   <tiles value='28'>K6.R2.K1.K7.K7.K5</tiles>
  </turn>
  <turn no='36' player='4' rpc-delay='0.0151617s'>
   <played>G8</played>
  <table>B2.B3.B4.B5.B6.B7-B6.B7.B8.B9.B10-K10.K11.K12.K13-B8.B9.B10.B11.B12.B13-G1.G2.G3.G4.G5.G6.G7.G8-G7.G8.G9.G10.G11.G12.G13-R11.G11.B11.K11-G1.B1.K1</table>
   <tiles value='32'>R9.K6.K4.R13</tiles>
  </turn>
  <turn no='37' player='1' rpc-delay='0.0550036s'>
   <played>K9</played>
  <table>B2.B3.B4.B5.B6.B7.B8.B9.B10.B11.B12.B13-B6.B7.B8.B9.B10-K9.K10.K11.K12.K13-G1.G2.G3.G4.G5.G6.G7.G8-G7.G8.G9.G10.G11.G12.G13-R11.G11.B11.K11-G1.B1.K1</table>
   <tiles value='33'>K2.R8.R12.R7.K2.G2</tiles>
  </turn>
  <turn no='38' player='2' rpc-delay='0.18059s'>
   <played>G9</played>
  <table>B2.B3.B4.B5.B6.B7.B8.B9.B10.B11.B12.B13-B6.B7.B8.B9.B10-K9.K10.K11.K12.K13-G1.G2.G3.G4.G5.G6.G7.G8.G9-G7.G8.G9.G10.G11.G12.G13-R11.G11.B11.K11-G1.B1.K1</table>
   <tiles value='48'>K4.R10.R11.G5.R8.B3.R4.R3</tiles>
  </turn>
  <turn no='39' player='3' rpc-delay='0.0227075s'>
   <played>K5.K6.K7</played>
  <table>B2.B3.B4.B5.B6.B7.B8.B9.B10.B11.B12.B13-B6.B7.B8.B9.B10-K9.K10.K11.K12.K13-G1.G2.G3.G4.G5.G6.G7.G8.G9-G7.G8.G9.G10.G11.G12.G13-R11.G11.B11.K11-G1.B1.K1-K5.K6.K7</table>
   <tiles value='10'>R2.K1.K7</tiles>
  </turn>
  <turn no='40' player='4' rpc-delay='0.0153821s'>
   <played>K4</played>
  <table>B2.B3.B4.B5.B6.B7.B8.B9.B10.B11.B12.B13-B6.B7.B8.B9.B10-K9.K10.K11.K12.K13-G1.G2.G3.G4.G5.G6.G7.G8.G9-G7.G8.G9.G10.G11.G12.G13-R11.G11.B11.K11-G1.B1.K1-K4.K5.K6.K7</table>
   <tiles value='28'>R9.K6.R13</tiles>
  </turn>
  <turn no='41' player='1' rpc-delay='0.0619763s'>
   <drawn>B4</drawn>
   <pool size='34'/>
   <tiles value='37'>K2.R8.R12.R7.K2.G2.B4</tiles>
  </turn>
  <turn no='42' player='2' rpc-delay='0.25528s'>
   <drawn>G4</drawn>
   <pool size='33'/>
   <tiles value='52'>K4.R10.R11.G5.R8.B3.R4.R3.G4</tiles>
  </turn>
  <turn no='43' player='3' rpc-delay='0.0254151s'>
   <drawn>B13</drawn>
   <pool size='32'/>
   <tiles value='23'>R2.K1.K7.B13</tiles>
  </turn>
  <turn no='44' player='4' rpc-delay='0.0120182s'>
   <drawn>K9</drawn>
   <pool size='31'/>
   <tiles value='37'>R9.K6.R13.K9</tiles>
  </turn>
  <turn no='45' player='1' rpc-delay='0.0558575s'>
   <played>B4</played>
  <table>B2.B3.B4-B6.B7.B8.B9.B10-K9.K10.K11.K12.K13-G1.G2.G3.G4.G5.G6.G7.G8.G9-G7.G8.G9.G10.G11.G12.G13-K4.K5.K6.K7-B4.B5.B6.B7.B8.B9.B10.B11.B12.B13-R11.G11.B11.K11-G1.B1.K1</table>
   <tiles value='33'>K2.R8.R12.R7.K2.G2</tiles>
  </turn>
  <turn no='46' player='2' rpc-delay='0.197408s'>
   <played>B3</played>
  <table>B2.B3.B4-B6.B7.B8.B9.B10-K9.K10.K11.K12.K13-G1.G2.G3.G4.G5.G6.G7.G8.G9-G7.G8.G9.G10.G11.G12.G13-K4.K5.K6.K7-B3.B4.B5.B6.B7.B8.B9.B10.B11.B12.B13-R11.G11.B11.K11-G1.B1.K1</table>
   <tiles value='49'>K4.R10.R11.G5.R8.R4.R3.G4</tiles>
  </turn>
  <turn no='47' player='3' rpc-delay='0.0230506s'>
   <drawn>R9</drawn>
   <pool size='30'/>
   <tiles value='32'>R2.K1.K7.B13.R9</tiles>
  </turn>
  <turn no='48' player='4' rpc-delay='0.01275s'>
   <drawn>K5</drawn>
   <pool size='29'/>
   <tiles value='42'>R9.K6.R13.K9.K5</tiles>
  </turn>
  <turn no='49' player='1' rpc-delay='0.0824662s'>
   <drawn>K3</drawn>
   <pool size='28'/>
   <tiles value='36'>K2.R8.R12.R7.K2.G2.K3</tiles>
  </turn>
  <turn no='50' player='2' rpc-delay='0.180458s'>
   <drawn>R13</drawn>
   <pool size='27'/>
   <tiles value='62'>K4.R10.R11.G5.R8.R4.R3.G4.R13</tiles>
  </turn>
  <turn no='51' player='3' rpc-delay='0.0227112s'>
   <drawn>G13</drawn>
   <pool size='26'/>
   <tiles value='45'>R2.K1.K7.B13.R9.G13</tiles>
  </turn>
  <turn no='52' player='4' rpc-delay='0.0129701s'>
   <drawn>G3</drawn>
   <pool size='25'/>
   <tiles value='45'>R9.K6.R13.K9.K5.G3</tiles>
  </turn>
  <turn no='53' player='1' rpc-delay='0.173087s'>
   <played>K2.K3</played>
  <table>B2.B3.B4-B6.B7.B8.B9.B10-K9.K10.K11.K12.K13-G1.G2.G3.G4.G5.G6.G7.G8.G9-G7.G8.G9.G10.G11.G12.G13-K2.K3.K4.K5.K6.K7-B3.B4.B5.B6.B7.B8.B9.B10.B11.B12.B13-R11.G11.B11.K11-G1.B1.K1</table>
   <tiles value='31'>R8.R12.R7.K2.G2</tiles>
  </turn>
  <turn no='54' player='2' rpc-delay='0.181814s'>
   <drawn>R1</drawn>
   <pool size='24'/>
   <tiles value='63'>K4.R10.R11.G5.R8.R4.R3.G4.R13.R1</tiles>
  </turn>
  <turn no='55' player='3' rpc-delay='0.0267916s'>
   <played>K1</played>
  <table>B2.B3.B4-B6.B7.B8.B9.B10-K9.K10.K11.K12.K13-G1.G2.G3.G4.G5.G6.G7.G8.G9-G7.G8.G9.G10.G11.G12.G13-K1.K2.K3.K4.K5.K6.K7-B3.B4.B5.B6.B7.B8.B9.B10.B11.B12.B13-R11.G11.B11.K11-G1.B1.K1</table>
   <tiles value='44'>R2.K7.B13.R9.G13</tiles>
  </turn>
  <turn no='56' player='4' rpc-delay='0.0136777s'>
   <played>G3.K5.K6</played>
  <table>B2.B3.B4-B6.B7.B8.B9.B10-K9.K10.K11.K12.K13-G1.G2.G3-G7.G8.G9.G10.G11.G12.G13-K1.K2.K3.K4.K5.K6-B3.B4.B5.B6.B7.B8.B9.B10.B11.B12.B13-R11.G11.B11.K11-G1.B1.K1-G3.G4.G5.G6.G7.G8.G9-K5.K6.K7</table>
   <tiles value='31'>R9.R13.K9</tiles>
  </turn>
  <turn no='57' player='1' rpc-delay='0.201691s'>
   <played>G2</played>
  <table>B2.B3.B4-B6.B7.B8.B9.B10-K9.K10.K11.K12.K13-G1.G2.G3-G7.G8.G9.G10.G11.G12.G13-K1.K2.K3.K4.K5.K6-B3.B4.B5.B6.B7.B8.B9.B10.B11.B12.B13-G2.G3.G4.G5.G6.G7.G8.G9-K5.K6.K7-R11.G11.B11.K11-G1.B1.K1</table>
   <tiles value='29'>R8.R12.R7.K2</tiles>
  </turn>
  <turn no='58' player='2' rpc-delay='0.180151s'>
   <played>G4.G5.K4</played>
  <table>B2.B3.B4-B6.B7.B8.B9.B10-K9.K10.K11.K12.K13-G1.G2.G3.G4.G5-G7.G8.G9.G10.G11.G12.G13-K1.K2.K3.K4.K5.K6-B3.B4.B5.B6.B7.B8.B9.B10.B11.B12.B13-G2.G3.G4.G5.G6.G7.G8.G9-K4.K5.K6.K7-R11.G11.B11.K11-G1.B1.K1</table>
   <tiles value='50'>R10.R11.R8.R4.R3.R13.R1</tiles>
  </turn>
  <turn no='59' player='3' rpc-delay='0.0236182s'>
   <played>K7</played>
  <table>B2.B3.B4-B6.B7.B8.B9.B10-K9.K10.K11.K12.K13-G1.G2.G3.G4.G5-G7.G8.G9.G10.G11.G12.G13-K1.K2.K3.K4.K5.K6.K7-B3.B4.B5.B6.B7.B8.B9.B10.B11.B12.B13-G2.G3.G4.G5.G6.G7.G8.G9-K4.K5.K6.K7-R11.G11.B11.K11-G1.B1.K1</table>
   <tiles value='37'>R2.B13.R9.G13</tiles>
  </turn>
  <turn no='60' player='4' rpc-delay='0.0132257s'>
   <drawn>G6</drawn>
   <pool size='23'/>
   <tiles value='37'>R9.R13.K9.G6</tiles>
  </turn>
  <turn no='61' player='1' rpc-delay='0.172594s'>
   <drawn>K3</drawn>
   <pool size='22'/>
   <tiles value='32'>R8.R12.R7.K2.K3</tiles>
  </turn>
  <turn no='62' player='2' rpc-delay='0.178922s'>
   <played>R1</played>
  <table>B2.B3.B4-B6.B7.B8.B9.B10-K9.K10.K11.K12.K13-G1.G2.G3.G4.G5-G7.G8.G9.G10.G11.G12.G13-K1.K2.K3.K4.K5.K6.K7-B3.B4.B5.B6.B7.B8.B9.B10.B11.B12.B13-G2.G3.G4.G5.G6.G7.G8.G9-K4.K5.K6.K7-R11.G11.B11.K11-R1.G1.B1.K1</table>
   <tiles value='49'>R10.R11.R8.R4.R3.R13</tiles>
  </turn>
  <turn no='63' player='3' rpc-delay='0.0226726s'>
   <drawn>B1</drawn>
   <pool size='21'/>
   <tiles value='38'>R2.B13.R9.G13.B1</tiles>
  </turn>
  <turn no='64' player='4' rpc-delay='0.0133634s'>
   <played>G6</played>
  <table>B2.B3.B4-B6.B7.B8.B9.B10-K9.K10.K11.K12.K13-G1.G2.G3.G4.G5.G6-G7.G8.G9.G10.G11.G12.G13-K1.K2.K3.K4.K5.K6.K7-B3.B4.B5.B6.B7.B8.B9.B10.B11.B12.B13-G2.G3.G4.G5.G6.G7.G8.G9-K4.K5.K6.K7-R11.G11.B11.K11-R1.G1.B1.K1</table>
   <tiles value='31'>R9.R13.K9</tiles>
  </turn>
  <turn no='65' player='1' rpc-delay='0.150406s'>
   <played>K2.K3</played>
  <table>B2.B3.B4-B6.B7.B8.B9.B10-K9.K10.K11.K12.K13-G1.G2.G3.G4.G5.G6.G7.G8.G9.G10.G11.G12.G13-K1.K2.K3.K4.K5.K6.K7-B3.B4.B5.B6.B7.B8.B9.B10.B11.B12.B13-G2.G3.G4.G5.G6.G7.G8.G9-K2.K3.K4.K5.K6.K7-R11.G11.B11.K11-R1.G1.B1.K1</table>
   <tiles value='27'>R8.R12.R7</tiles>
  </turn>
  <turn no='66' player='2' rpc-delay='0.17729s'>
   <drawn>K12</drawn>
   <pool size='20'/>
   <tiles value='61'>R10.R11.R8.R4.R3.R13.K12</tiles>
  </turn>
  <turn no='67' player='3' rpc-delay='0.0362567s'>
   <played>B1</played>
  <table>B1.B2.B3.B4-B6.B7.B8.B9.B10-K9.K10.K11.K12.K13-G1.G2.G3.G4.G5.G6.G7.G8.G9.G10.G11.G12.G13-K1.K2.K3.K4.K5.K6.K7-B3.B4.B5.B6.B7.B8.B9.B10.B11.B12.B13-G2.G3.G4.G5.G6.G7.G8.G9-K2.K3.K4.K5.K6.K7-R11.G11.B11.K11-R1.G1.B1.K1</table>
   <tiles value='37'>R2.B13.R9.G13</tiles>
  </turn>
  <turn no='68' player='4' rpc-delay='0.0132589s'>
   <drawn>R6</drawn>
   <pool size='19'/>
   <tiles value='37'>R9.R13.K9.R6</tiles>
  </turn>
  <turn no='69' player='1' rpc-delay='0.278223s'>
   <drawn>R3</drawn>
   <pool size='18'/>
   <tiles value='30'>R8.R12.R7.R3</tiles>
  </turn>
  <turn no='70' player='2' rpc-delay='0.180301s'>
   <drawn>R12</drawn>
   <pool size='17'/>
   <tiles value='73'>R10.R11.R8.R4.R3.R13.K12.R12</tiles>
  </turn>
  <turn no='71' player='3' rpc-delay='0.0232799s'>
   <drawn>R7</drawn>
   <pool size='16'/>
   <tiles value='44'>R2.B13.R9.G13.R7</tiles>
  </turn>
  <turn no='72' player='4' rpc-delay='0.0133835s'>
   <drawn>R1</drawn>
   <pool size='15'/>
   <tiles value='38'>R9.R13.K9.R6.R1</tiles>
  </turn>
  <turn no='73' player='1' rpc-delay='0.265187s'>
   <drawn>R5</drawn>
   <pool size='14'/>
   <tiles value='35'>R8.R12.R7.R3.R5</tiles>
  </turn>
  <turn no='74' player='2' rpc-delay='0.199713s'>
   <drawn>K8</drawn>
   <pool size='13'/>
   <tiles value='81'>R10.R11.R8.R4.R3.R13.K12.R12.K8</tiles>
  </turn>
  <turn no='75' player='3' rpc-delay='0.0251902s'>
   <drawn>G12</drawn>
   <pool size='12'/>
   <tiles value='56'>R2.B13.R9.G13.R7.G12</tiles>
  </turn>
  <turn no='76' player='4' rpc-delay='0.0142408s'>
   <played>R1</played>
  <table>B2.B3.B4-B6.B7.B8.B9.B10-K9.K10.K11.K12.K13-G2.G3.G4.G5.G6.G7.G8.G9.G10.G11.G12.G13-K2.K3.K4.K5.K6.K7-B3.B4.B5.B6.B7.B8.B9.B10.B11.B12.B13-G2.G3.G4.G5.G6.G7.G8.G9-K2.K3.K4.K5.K6.K7-R11.G11.B11.K11-R1.G1.B1.K1-R1.G1.B1.K1</table>
   <tiles value='37'>R9.R13.K9.R6</tiles>
  </turn>
  <turn no='77' player='1' rpc-delay='0.11539s'>
   <drawn>K13</drawn>
   <pool size='11'/>
   <tiles value='48'>R8.R12.R7.R3.R5.K13</tiles>
  </turn>
  <turn no='78' player='2' rpc-delay='0.179545s'>
   <played>K8</played>
  <table>B2.B3.B4-B6.B7.B8.B9.B10-K8.K9.K10.K11.K12.K13-G2.G3.G4.G5.G6.G7.G8.G9.G10.G11.G12.G13-K2.K3.K4.K5.K6.K7-B3.B4.B5.B6.B7.B8.B9.B10.B11.B12.B13-G2.G3.G4.G5.G6.G7.G8.G9-K2.K3.K4.K5.K6.K7-R11.G11.B11.K11-R1.G1.B1.K1-R1.G1.B1.K1</table>
   <tiles value='73'>R10.R11.R8.R4.R3.R13.K12.R12</tiles>
  </turn>
  <turn no='79' player='3' rpc-delay='0.0229176s'>
   <drawn>K8</drawn>
   <pool size='10'/>
   <tiles value='64'>R2.B13.R9.G13.R7.G12.K8</tiles>
  </turn>
  <turn no='80' player='4' rpc-delay='0.0142112s'>
   <played>K9</played>
  <table>B2.B3.B4-B6.B7.B8.B9.B10-K9.K10.K11.K12.K13-G2.G3.G4.G5.G6.G7.G8.G9.G10.G11.G12.G13-K2.K3.K4.K5.K6-B3.B4.B5.B6.B7.B8.B9.B10.B11.B12.B13-G2.G3.G4.G5.G6.G7.G8.G9-K2.K3.K4.K5.K6.K7-R11.G11.B11.K11-R1.G1.B1.K1-R1.G1.B1.K1-K7.K8.K9</table>
   <tiles value='28'>R9.R13.R6</tiles>
  </turn>
  <turn no='81' player='1' rpc-delay='0.925359s'>
   <drawn>B5</drawn>
   <pool size='9'/>
   <tiles value='53'>R8.R12.R7.R3.R5.K13.B5</tiles>
  </turn>
  <turn no='82' player='2' rpc-delay='0.190485s'>
   <drawn>B12</drawn>
   <pool size='8'/>
   <tiles value='85'>R10.R11.R8.R4.R3.R13.K12.R12.B12</tiles>
  </turn>
  <turn no='83' player='3' rpc-delay='0.0242374s'>
   <played>K8</played>
  <table>B2.B3.B4-B6.B7.B8.B9.B10-K8.K9.K10.K11.K12.K13-G2.G3.G4.G5.G6.G7.G8.G9.G10.G11.G12.G13-K2.K3.K4.K5.K6-B3.B4.B5.B6.B7.B8.B9.B10.B11.B12.B13-G2.G3.G4.G5.G6.G7.G8.G9-K2.K3.K4.K5.K6.K7-R11.G11.B11.K11-R1.G1.B1.K1-R1.G1.B1.K1-K7.K8.K9</table>
   <tiles value='56'>R2.B13.R9.G13.R7.G12</tiles>
  </turn>
  <turn no='84' player='4' rpc-delay='0.0133852s'>
   <drawn>G10</drawn>
   <pool size='7'/>
   <tiles value='38'>R9.R13.R6.G10</tiles>
  </turn>
  <turn no='85' player='1' rpc-delay='1.6086s'>
   <played>B5</played>
  <table>B2.B3.B4.B5-B6.B7.B8.B9.B10-K2.K3.K4.K5.K6.K7.K8.K9.K10.K11.K12.K13-G2.G3.G4.G5.G6.G7.G8.G9.G10.G11.G12.G13-K2.K3.K4.K5.K6-B3.B4.B5.B6.B7.B8.B9.B10.B11.B12.B13-G2.G3.G4.G5.G6.G7.G8.G9-K7.K8.K9-R11.G11.B11.K11-R1.G1.B1.K1-R1.G1.B1.K1</table>
   <tiles value='48'>R8.R12.R7.R3.R5.K13</tiles>
  </turn>
  <turn no='86' player='2' rpc-delay='0.193157s'>
   <drawn>K10</drawn>
   <pool size='6'/>
   <tiles value='95'>R10.R11.R8.R4.R3.R13.K12.R12.B12.K10</tiles>
  </turn>
  <turn no='87' player='3' rpc-delay='0.022786s'>
   <drawn>R6</drawn>
   <pool size='5'/>
   <tiles value='62'>R2.B13.R9.G13.R7.G12.R6</tiles>
  </turn>
  <turn no='88' player='4' rpc-delay='0.0141296s'>
   <played>G10</played>
  <table>B2.B3.B4.B5-B6.B7.B8.B9.B10-K2.K3.K4.K5.K6.K7.K8.K9.K10.K11.K12.K13-G2.G3.G4.G5.G6.G7.G8.G9.G10-K2.K3.K4.K5.K6-B3.B4.B5.B6.B7.B8.B9.B10.B11.B12.B13-G2.G3.G4.G5.G6.G7.G8.G9-K7.K8.K9-R11.G11.B11.K11-R1.G1.B1.K1-R1.G1.B1.K1-G10.G11.G12.G13</table>
   <tiles value='28'>R9.R13.R6</tiles>
  </turn>
  <turn no='89' player='1' rpc-delay='0.67363s'>
   <drawn>R4</drawn>
   <pool size='4'/>
   <tiles value='52'>R8.R12.R7.R3.R5.K13.R4</tiles>
  </turn>
  <turn no='90' player='2' rpc-delay='0.198066s'>
   <played>K10</played>
  <table>B2.B3.B4.B5-B6.B7.B8.B9.B10-K2.K3.K4.K5.K6.K7.K8.K9.K10.K11.K12.K13-G2.G3.G4.G5.G6.G7.G8.G9.G10-K2.K3.K4.K5.K6-B3.B4.B5.B6.B7.B8.B9.B10.B11.B12.B13-G2.G3.G4.G5.G6.G7.G8.G9-K7.K8.K9.K10-R11.G11.B11.K11-R1.G1.B1.K1-R1.G1.B1.K1-G10.G11.G12.G13</table>
   <tiles value='85'>R10.R11.R8.R4.R3.R13.K12.R12.B12</tiles>
  </turn>
  <turn no='91' player='3' rpc-delay='0.0225274s'>
   <drawn>B2</drawn>
   <pool size='3'/>
   <tiles value='64'>R2.B13.R9.G13.R7.G12.R6.B2</tiles>
  </turn>
  <turn no='92' player='4' rpc-delay='0.0127115s'>
   <drawn>R5</drawn>
   <pool size='2'/>
   <tiles value='33'>R9.R13.R6.R5</tiles>
  </turn>
  <turn no='93' player='1' rpc-delay='0.313665s'>
   <played>R3.R4.R5</played>
  <table>B2.B3.B4.B5.B6.B7.B8.B9.B10-K2.K3.K4.K5.K6.K7.K8.K9.K10.K11.K12.K13-G2.G3.G4.G5.G6.G7.G8.G9.G10-K2.K3.K4.K5.K6.K7.K8.K9.K10.K11-B3.B4.B5.B6.B7.B8.B9.B10.B11.B12.B13-G2.G3.G4.G5.G6.G7.G8.G9-G10.G11.G12.G13-R3.R4.R5-R11.G11.B11-R1.G1.B1.K1-R1.G1.B1.K1</table>
   <tiles value='40'>R8.R12.R7.K13</tiles>
  </turn>
  <turn no='94' player='2' rpc-delay='0.180202s'>
   <played>K12</played>
  <table>B2.B3.B4.B5.B6.B7.B8.B9.B10-K2.K3.K4.K5.K6.K7.K8.K9.K10.K11.K12.K13-G2.G3.G4.G5.G6.G7.G8.G9.G10-K2.K3.K4.K5.K6.K7.K8.K9.K10.K11.K12-B3.B4.B5.B6.B7.B8.B9.B10.B11.B12.B13-G2.G3.G4.G5.G6.G7.G8.G9-G10.G11.G12.G13-R3.R4.R5-R11.G11.B11-R1.G1.B1.K1-R1.G1.B1.K1</table>
   <tiles value='73'>R10.R11.R8.R4.R3.R13.R12.B12</tiles>
  </turn>
  <turn no='95' player='3' rpc-delay='0.0240263s'>
   <played>R2.B2</played>
  <table>B2.B3.B4.B5.B6.B7.B8.B9.B10-K2.K3.K4.K5.K6.K7.K8.K9.K10.K11.K12.K13-G2.G3.G4.G5.G6.G7.G8.G9.G10-K2.K3.K4.K5.K6.K7.K8.K9.K10.K11.K12-B2.B3.B4.B5.B6.B7.B8.B9.B10.B11.B12.B13-G2.G3.G4.G5.G6.G7.G8.G9-G10.G11.G12.G13-R2.R3.R4.R5-R11.G11.B11-R1.G1.B1.K1-R1.G1.B1.K1</table>
   <tiles value='60'>B13.R9.G13.R7.G12.R6</tiles>
  </turn>
  <turn no='96' player='4' rpc-delay='0.0135712s'>
   <played>R6</played>
  <table>B2.B3.B4.B5.B6.B7.B8.B9.B10-K2.K3.K4.K5.K6.K7.K8.K9.K10.K11.K12.K13-G2.G3.G4.G5.G6.G7.G8.G9.G10-K2.K3.K4.K5.K6.K7.K8.K9.K10.K11.K12-B2.B3.B4.B5.B6.B7.B8.B9.B10.B11.B12.B13-G2.G3.G4.G5.G6.G7.G8.G9-G10.G11.G12.G13-R2.R3.R4.R5.R6-R11.G11.B11-R1.G1.B1.K1-R1.G1.B1.K1</table>
   <tiles value='27'>R9.R13.R5</tiles>
  </turn>
  <turn no='97' player='1' rpc-delay='0.10298s'>
   <played>R7.R8.K13</played>
  <table>B2.B3.B4.B5.B6.B7.B8.B9.B10-K2.K3.K4.K5.K6.K7.K8.K9.K10.K11.K12.K13-G2.G3.G4.G5.G6.G7.G8.G9.G10-K2.K3.K4.K5.K6.K7.K8.K9.K10.K11.K12.K13-B2.B3.B4.B5.B6.B7.B8.B9.B10.B11.B12.B13-G2.G3.G4.G5.G6.G7.G8.G9.G10.G11.G12.G13-R2.R3.R4.R5.R6.R7.R8-R11.G11.B11-R1.G1.B1.K1-R1.G1.B1.K1</table>
   <tiles value='12'>R12</tiles>
  </turn>
  <turn no='98' player='2' rpc-delay='0.180058s'>
   <drawn>R2</drawn>
   <pool size='1'/>
   <tiles value='75'>R10.R11.R8.R4.R3.R13.R12.B12.R2</tiles>
  </turn>
  <turn no='99' player='3' rpc-delay='0.0251486s'>
   <played>R7.R9</played>
  <table>B2.B3.B4.B5.B6.B7.B8.B9.B10-K2.K3.K4.K5.K6.K7.K8.K9.K10.K11.K12.K13-G2.G3.G4.G5.G6.G7.G8.G9.G10-K2.K3.K4.K5.K6.K7.K8.K9.K10.K11.K12.K13-B2.B3.B4.B5.B6.B7.B8.B9.B10.B11.B12.B13-G2.G3.G4.G5.G6.G7.G8.G9.G10.G11.G12.G13-R2.R3.R4.R5.R6.R7-R7.R8.R9-R11.G11.B11-R1.G1.B1.K1-R1.G1.B1.K1</table>
   <tiles value='44'>B13.G13.G12.R6</tiles>
  </turn>
  <turn no='100' player='4' rpc-delay='0.0140732s'>
   <played>R5</played>
  <table>B2.B3.B4.B5.B6.B7.B8.B9.B10-K2.K3.K4.K5.K6.K7.K8.K9.K10.K11.K12.K13-G2.G3.G4.G5.G6.G7.G8.G9.G10-K2.K3.K4.K5.K6.K7.K8.K9.K10.K11.K12.K13-B2.B3.B4.B5.B6.B7.B8.B9.B10.B11.B12.B13-G2.G3.G4.G5.G6.G7.G8.G9.G10.G11.G12.G13-R2.R3.R4.R5-R7.R8.R9-R11.G11.B11-R1.G1.B1.K1-R1.G1.B1.K1-R5.R6.R7</table>
   <tiles value='22'>R9.R13</tiles>
  </turn>
  <turn no='101' player='1' rpc-delay='0.139734s'>
   <drawn>R10</drawn>
   <pool size='0'/>
   <tiles value='22'>R12.R10</tiles>
  </turn>
  <turn no='102' player='2' rpc-delay='0.18462s'>
   <played>R3.R4.R8.R10.R11</played>
  <table>B2.B3.B4.B5.B6.B7.B8.B9.B10-K2.K3.K4.K5.K6.K7.K8.K9.K10.K11.K12.K13-G2.G3.G4.G5.G6.G7.G8.G9.G10-K2.K3.K4.K5.K6.K7.K8.K9.K10.K11.K12.K13-B2.B3.B4.B5.B6.B7.B8.B9.B10.B11.B12.B13-G2.G3.G4.G5.G6.G7.G8.G9.G10.G11.G12.G13-R2.R3.R4.R5-R7.R8.R9.R10.R11-R11.G11.B11-R1.G1.B1.K1-R1.G1.B1.K1-R3.R4.R5.R6.R7.R8</table>
   <tiles value='39'>R13.R12.B12.R2</tiles>
  </turn>
  <turn no='103' player='3' rpc-delay='0.0241251s'>
   <played>R6</played>
  <table>B2.B3.B4.B5.B6.B7.B8.B9.B10-K2.K3.K4.K5.K6.K7.K8.K9.K10.K11.K12.K13-G2.G3.G4.G5.G6.G7.G8.G9.G10-K2.K3.K4.K5.K6.K7.K8.K9.K10.K11.K12.K13-B2.B3.B4.B5.B6.B7.B8.B9.B10.B11.B12.B13-G2.G3.G4.G5.G6.G7.G8.G9.G10.G11.G12.G13-R2.R3.R4.R5.R6-R7.R8.R9.R10.R11-R11.G11.B11-R1.G1.B1.K1-R1.G1.B1.K1-R3.R4.R5.R6.R7.R8</table>
   <tiles value='38'>B13.G13.G12</tiles>
  </turn>
  <turn no='104' player='4' rpc-delay='0.0143696s'>
   <played>R9</played>
  <table>B2.B3.B4.B5.B6.B7.B8.B9.B10-K2.K3.K4.K5.K6.K7.K8.K9.K10.K11.K12.K13-G2.G3.G4.G5.G6.G7.G8.G9.G10-K2.K3.K4.K5.K6.K7.K8.K9.K10.K11.K12.K13-B2.B3.B4.B5.B6.B7.B8.B9.B10.B11.B12.B13-G2.G3.G4.G5.G6.G7.G8.G9.G10.G11.G12.G13-R2.R3.R4.R5.R6-R7.R8.R9-R11.G11.B11-R1.G1.B1.K1-R1.G1.B1.K1-R3.R4.R5.R6.R7.R8-R9.R10.R11</table>
   <tiles value='13'>R13</tiles>
  </turn>
  <turn no='105' player='1' rpc-delay='0.265947s'>
   <played>R10.R12</played>
  <table>B2.B3.B4.B5.B6.B7.B8.B9.B10-K2.K3.K4.K5.K6.K7.K8.K9.K10.K11.K12.K13-G2.G3.G4.G5.G6.G7.G8.G9.G10-K2.K3.K4.K5.K6.K7.K8.K9.K10.K11.K12.K13-B2.B3.B4.B5.B6.B7.B8.B9.B10.B11.B12.B13-G2.G3.G4.G5.G6.G7.G8.G9.G10.G11.G12.G13-R2.R3.R4.R5.R6.R7.R8.R9.R10-R3.R4.R5.R6.R7.R8-R9.R10.R11.R12-R11.G11.B11-R1.G1.B1.K1-R1.G1.B1.K1</table>
   <tiles value='0'></tiles>
  </turn>
 </turns>

 <scores>
  <score player='1'>0</score>
  <score player='2'>39</score>
  <score player='3'>38</score>
  <score player='4'>13</score>
 </scores>
</rummikub-transcript>
